<?xml version="1.0" encoding="UTF-8"?>
<base:SpatialDataSet xmlns:base="urn:x-inspire:specification:gmlas:BaseTypes:3.2" 
xmlns:gmd="http://www.isotc211.org/2005/gmd" 
xmlns:gml="http://www.opengis.net/gml/3.2" 
xmlns:gn="urn:x-inspire:specification:gmlas:GeographicalNames:3.0" 
xmlns:ps="urn:x-inspire:specification:gmlas:ProtectedSites:3.0" 
xmlns:gco="http://www.isotc211.org/2005/gco" 
xmlns:xlink="http://www.w3.org/1999/xlink" 
xmlns:xsi="http://www.w3.org/2001/XMLSchema-instance"
xmlns:gss="http://www.isotc211.org/2005/gss" 
xmlns:gsr="http://www.isotc211.org/2005/gsr" 
xmlns:gts="http://www.isotc211.org/2005/gts" 
xsi:schemaLocation="urn:x-inspire:specification:gmlas:BaseTypes:3.2 http://inspire.ec.europa.eu/schemas/base/3.2/BaseTypes.xsd
urn:x-inspire:specification:gmlas:ProtectedSites:3.0 http://inspire.ec.europa.eu/schemas/ps/3.0/ProtectedSites.xsd                      
urn:x-inspire:specification:gmlas:GeographicalNames:3.0 http://inspire.ec.europa.eu/schemas/gn/3.0/GeographicalNames.xsd" 
 gml:id="NL.DLG.PS">
  <base:identifier>
    <base:Identifier>
      <base:localId>0</base:localId>
      <base:namespace>NL.DLG.PS</base:namespace>
    </base:Identifier>
  </base:identifier>
  <base:metadata xsi:nil="true"/>
  <base:member>
<ps:ProtectedSite xmlns:base="urn:x-inspire:specification:gmlas:BaseTypes:3.2" xmlns:gmd="http://www.isotc211.org/2005/gmd" xmlns:gml="http://www.opengis.net/gml/3.2" xmlns:gn="urn:x-inspire:specification:gmlas:GeographicalNames:3.0" xmlns:ps="urn:x-inspire:specification:gmlas:ProtectedSites:3.0" xmlns:gco="http://www.isotc211.org/2005/gco" xmlns:xlink="http://www.w3.org/1999/xlink" xmlns:xsi="http://www.w3.org/2001/XMLSchema-instance" xmlns:gss="http://www.isotc211.org/2005/gss" xmlns:gsr="http://www.isotc211.org/2005/gsr" xmlns:gts="http://www.isotc211.org/2005/gts" xsi:schemaLocation="urn:x-inspire:specification:gmlas:BaseTypes:3.2 http://inspire.ec.europa.eu/schemas/base/3.2/BaseTypes.xsd urn:x-inspire:specification:gmlas:ProtectedSites:3.0 http://inspire.ec.europa.eu/schemas/ps/3.0/ProtectedSites.xsd                       urn:x-inspire:specification:gmlas:GeographicalNames:3.0 http://inspire.ec.europa.eu/schemas/gn/3.0/GeographicalNames.xsd" gml:id="id-f6d54c36-42d5-4de4-aa2f-46fa4987640e">
<gml:identifier codeSpace="http://inspire.jrc.ec.europa.eu/">urn:x-inspire:object:id:NL.PS.N2000
</gml:identifier>
  <gml:name codeSpace=""><!-- String value. --></gml:name>
  <gml:boundedBy nilReason="">
    <gml:Envelope srsName="EPSG:4258" srsDimension="2" axisLabels="" uomLabels="">
      <gml:lowerCorner srsName="EPSG:4258" srsDimension="2" axisLabels="" uomLabels="">2.0 50.0</gml:lowerCorner>
      <gml:upperCorner srsName="EPSG:4258" srsDimension="2" axisLabels="" uomLabels="">8.0 56.0</gml:upperCorner>
      <!-- End Choice 2 -->
    </gml:Envelope>
    <!-- End Choice 1 -->
  </gml:boundedBy>
  <gml:location nilReason="" gml:remoteSchema="" xlink:type="simple" xlink:href="" xlink:title="" xlink:show="other" xlink:actuate="other">
        <gml:MultiSurface aggregationType="table" srsName="EPSG:4258" srsDimension="2" axisLabels="" uomLabels="" gml:id="id-f6d54c36-42d5-4de4-aa2f-46fa4987640eG">
      <!-- AggregationType moet nog gecontroleerd worden -->
      <gml:metaDataProperty about="" nilReason="" gml:remoteSchema="" xlink:type="simple" xlink:href="" xlink:title="" xlink:show="other" xlink:actuate="other">
        <gml:GenericMetaData gml:id="id-f6d54c36-42d5-4de4-aa2f-46fa4987640eMD">
        </gml:GenericMetaData>
      </gml:metaDataProperty>
      <gml:description nilReason="" gml:remoteSchema="" xlink:type="simple" xlink:href="" xlink:title="" xlink:show="other" xlink:actuate="other"><!-- String value. --></gml:description>
      <gml:descriptionReference owns="false" nilReason="" gml:remoteSchema="" xlink:type="simple" xlink:href="" xlink:title="" xlink:show="other" xlink:actuate="other"/>
      <gml:identifier codeSpace="">NL3000070NL3000070</gml:identifier>
      <gml:name codeSpace=""><!-- String value. --></gml:name>
      <gml:surfaceMember nilReason="" gml:remoteSchema="" xlink:type="simple" xlink:href="" xlink:title="" xlink:show="other" xlink:actuate="other" owns="false">
      </gml:surfaceMember>
    </gml:MultiSurface>
  </gml:location>
  <ps:geometry nilReason="" gml:remoteSchema="" xlink:type="simple" xlink:href="" xlink:title="" xlink:show="other" xlink:actuate="other" owns="false">
    <gml:MultiSurface aggregationType="table" srsName="EPSG:4258" srsDimension="2" axisLabels="" uomLabels="" gml:id="id-f6d54c36-42d5-4de4-aa2f-46fa4987640eG2">
      <!-- AggregationType moet nog gecontroleerd worden -->
      <gml:metaDataProperty about="" nilReason="" gml:remoteSchema="" xlink:type="simple" xlink:href="" xlink:title="" xlink:show="other" xlink:actuate="other">
        <gml:GenericMetaData gml:id="id-f6d54c36-42d5-4de4-aa2f-46fa4987640eMD2">
        </gml:GenericMetaData>
      </gml:metaDataProperty>
            <gml:surfaceMember>
      <gml:Surface gml:id="id-f6d54c36-42d5-4de4-aa2f-46fa4987640eS">
      <gml:patches>
<gml:PolygonPatch>
<gml:exterior>
<gml:LinearRing>
<gml:posList>6.439216527 52.840833448 6.439157619 52.840842955 6.439027089 52.840863767 6.438895185 52.840885151 6.437344786 52.841161691 6.436219038 52.840889061 6.436031919 52.840822741 6.436032124 52.840821616 6.435463034 52.840764269 6.43538441 52.840754289 6.435265851 52.840742411 6.435238737 52.840839825 6.433922184 52.840713767 6.432924077 52.840618048 6.432870789 52.840620201 6.432627107 52.841097539 6.432487278 52.841068994 6.432381787 52.84105082 6.432056696 52.840965482 6.431259171 52.840742729 6.429983636 52.840381481 6.429599139 52.840274748 6.429549891 52.840242037 6.429460004 52.840138908 6.429389683 52.84003954 6.429263757 52.839922682 6.429109333 52.839826295 6.428380391 52.839395093 6.428288204 52.839331303 6.428274709 52.839310076 6.428270713 52.839278655 6.428305575 52.839242963 6.42830826 52.839219348 6.428301392 52.83920368 6.42827186 52.839190457 6.428161438 52.839169515 6.427966039 52.839124598 6.427816158 52.839082656 6.427639806 52.839019598 6.427548066 52.838974901 6.427452821 52.838918999 6.427396749 52.838872305 6.42736656 52.838831565 6.427332931 52.838772878 6.427306456 52.838751764 6.427159543 52.838697999 6.426702499 52.838543022 6.426337463 52.838434425 6.426052698 52.83835658 6.425932252 52.838323366 6.42573788 52.838272821 6.42515335 52.838129618 6.424754407 52.838038163 6.423499783 52.837760919 6.42333811 52.837729745 6.423306584 52.837720469 6.423200078 52.837688255 6.423247388 52.837610329 6.42328027 52.837569038 6.423387609 52.837557994 6.42352997 52.837537659 6.423565798 52.837532854 6.423747485 52.837498696 6.423864598 52.837469593 6.424066896 52.837404923 6.424297635 52.837327088 6.424552823 52.837233872 6.424822128 52.83712986 6.425222468 52.836967975 6.425339449 52.836923707 6.425527419 52.836861406 6.425722435 52.836792864 6.425954551 52.836704903 6.426012758 52.836675748 6.42605655 52.836645034 6.426115608 52.836602952 6.426108744 52.836587286 6.426140315 52.836559488 6.426223446 52.836515512 6.426453972 52.836409588 6.426825732 52.836245701 6.427062841 52.83614365 6.427123342 52.836103805 6.427486127 52.835845625 6.427646151 52.835749299 6.427696897 52.835718525 6.427725189 52.83569918 6.427950656 52.835546675 6.42802592 52.835493781 6.428139517 52.835414711 6.428302241 52.835314993 6.428340774 52.835297243 6.428261947 52.835249064 6.428870418 52.834841007 6.428729924 52.834822575 6.428283732 52.834771417 6.428147246 52.834755765 6.427545936 52.833252833 6.427634574 52.833197013 6.427659074 52.833174331 6.428064295 52.832917466 6.428947945 52.832353098 6.429046912 52.832302804 6.428378302 52.831955892 6.427315436 52.831409644 6.426818442 52.831151098 6.426734878 52.831108013 6.425869732 52.830655515 6.425420725 52.830425195 6.424798782 52.830098078 6.423551846 52.829441054 6.422309744 52.828781166 6.421814102 52.828528207 6.421250116 52.828247753 6.421082764 52.828180676 6.420894278 52.828112098 6.420784088 52.828079912 6.420686264 52.82805099 6.420634255 52.82803796 6.420044985 52.827913311 6.418330505 52.827519228 6.417660143 52.827366622 6.417539635 52.827339018 6.416719879 52.827152872 6.415502635 52.826872413 6.414569909 52.826652961 6.414042064 52.82653618 6.413758571 52.826458859 6.413474665 52.826403448 6.412689736 52.826257419 6.411827465 52.826105306 6.409513315 52.825707823 6.409451995 52.825672962 6.409400708 52.825650933 6.409377566 52.825642705 6.409349972 52.82567215 6.409210893 52.825633462 6.409165042 52.82563554 6.408214888 52.825471237 6.407886738 52.825416753 6.407754009 52.825401599 6.407694171 52.825400427 6.407711137 52.825382307 6.40800591 52.825188804 6.408109947 52.825117138 6.40817743 52.825048593 6.408211362 52.824992694 6.408232397 52.824920616 6.408246926 52.82483792 6.408284841 52.82466459 6.40830168 52.824462231 6.408316545 52.824334598 6.408315365 52.824284054 6.408295132 52.824241536 6.408251834 52.824194163 6.40816648 52.824132545 6.408098856 52.824085941 6.408046842 52.824042574 6.408021261 52.82398943 6.407998349 52.82391155 6.407984648 52.823851003 6.407916401 52.823588708 6.407872031 52.823435741 6.407841228 52.823367477 6.407800409 52.823326823 6.407749931 52.823289619 6.407678831 52.823262705 6.407492123 52.823218804 6.407286666 52.823176188 6.407097236 52.823144669 6.406982349 52.823128799 6.4068802 52.823122371 6.406728352 52.823121984 6.406466367 52.823130404 6.406179891 52.8231424 6.406006508 52.82316298 6.405887763 52.823190396 6.405757593 52.823244869 6.405630623 52.823317291 6.405544071 52.82336353 6.405410421 52.823407922 6.405272485 52.823427635 6.405163128 52.823430255 6.405077951 52.823425928 6.404949983 52.823405673 6.404762165 52.823353915 6.404424809 52.823271415 6.40382086 52.823118726 6.40333883 52.822995329 6.403193705 52.82296511 6.403086848 52.822955347 6.402968799 52.822952983 6.402731394 52.822961744 6.402422785 52.822978977 6.40217722 52.822995672 6.40169014 52.823023973 6.401576281 52.823042354 6.401473472 52.823067383 6.401382461 52.823101297 6.40130703 52.823137327 6.401285363 52.823152676 6.401240511 52.823187884 6.401182382 52.823250166 6.401120557 52.823333263 6.401062228 52.823437113 6.401007858 52.823561711 6.400923774 52.823804522 6.40082379 52.824071621 6.400790187 52.824142119 6.400722549 52.824244363 6.400625464 52.824316524 6.400466184 52.824425725 6.400253344 52.82456459 6.400077876 52.824685725 6.39982498 52.824846835 6.399583002 52.825008977 6.399156226 52.825290082 6.399044211 52.825348327 6.398932458 52.825427914 6.398816432 52.825523265 6.398492704 52.82555915 6.398156099 52.82559964 6.39793631 52.825629026 6.397732075 52.825659405 6.397548639 52.825696907 6.397486844 52.825681142 6.397434604 52.825637772 6.39735719 52.825558105 6.397318616 52.825524167 6.397265783 52.825515066 6.396918768 52.825456218 6.396713958 52.82542144 6.396315178 52.825339437 6.396012965 52.825272905 6.396207368 52.824846612 6.39632892 52.824568661 6.396349788 52.824528605 6.396273738 52.824417468 6.396147576 52.82426463 6.395802717 52.823846268 6.39525529 52.823177974 6.395071406 52.822944175 6.394847624 52.822659034 6.394218111 52.821887515 6.39378235 52.821345217 6.39363353 52.821174029 6.393514495 52.821158746 6.393510107 52.821169454 6.39347931 52.821241612 6.393457764 52.821292348 6.393398469 52.821405189 6.393321804 52.821528851 6.393281647 52.821576934 6.393235622 52.821631808 6.393163319 52.821713304 6.393058324 52.821814734 6.392953007 52.821902125 6.392841265 52.821982269 6.392703318 52.822072184 6.392502618 52.822174981 6.392441123 52.822202462 6.392407054 52.822192638 6.392360675 52.822151463 6.392277118 52.822056115 6.392166727 52.821922799 6.392120656 52.821874881 6.392063421 52.82181526 6.391950431 52.821710051 6.39183806 52.821631798 6.391726158 52.821573761 6.39158514 52.821519902 6.391344724 52.821457893 6.391082975 52.821385389 6.390958405 52.821340941 6.390896368 52.82132461 6.390834102 52.821308285 6.390694232 52.821284184 6.39065118 52.821276683 6.3904038 52.821264723 6.389542648 52.821214109 6.388569013 52.821161066 6.387835976 52.821117228 6.387061387 52.821070928 6.386941891 52.82106575 6.386791056 52.82105859 6.386571505 52.821046948 6.385321263 52.820970358 6.384789074 52.82094111 6.383226149 52.820854755 6.383032582 52.820844014 6.38118023 52.820730842 6.380884975 52.820713081 6.379611145 52.820617528 6.379506278 52.820613344 6.379249108 52.820610548 6.378783929 52.82062104 6.378073708 52.820632001 6.377736873 52.820640977 6.377550387 52.820645897 6.377154338 52.820650309 6.377083884 52.820650894 6.3768755 52.820640829 6.376642553 52.820620855 6.376241025 52.820567453 6.374992589 52.820394689 6.374553373 52.820324745 6.374433807 52.820295964 6.374350372 52.820275871 6.374241288 52.820249251 6.373736982 52.820098955 6.373207696 52.819930328 6.372951883 52.819883012 6.37281407 52.819877413 6.37271756 52.819873717 6.37261478 52.819869512 6.372037323 52.819918656 6.371973227 52.819923679 6.371488479 52.819982727 6.37126828 52.820024428 6.371150967 52.820054042 6.371055316 52.820078423 6.3709479 52.82010515 6.370613512 52.820202273 6.370402753 52.820271978 6.370153107 52.820375143 6.369840185 52.820519832 6.369516706 52.820679774 6.369319994 52.82081789 6.369125353 52.820965535 6.369077164 52.821008059 6.368963286 52.821108419 6.368817994 52.821244985 6.368618175 52.82135841 6.368586361 52.821541787 6.368584006 52.821591797 6.36855936 52.82159874 6.368368878 52.821467185 6.368350923 52.821452166 6.36825571 52.821372064 6.368172774 52.821301972 6.367965428 52.821141907 6.367761964 52.821103138 6.367569272 52.821069336 6.365726308 52.820710941 6.36544553 52.820666624 6.364776908 52.820537299 6.364411638 52.82046671 6.363939732 52.820375086 6.363472493 52.820284546 6.362553117 52.820105023 6.362456731 52.82008615 6.362004597 52.819997168 6.361626785 52.819924986 6.361575166 52.819928218 6.361432324 52.819936125 6.361141306 52.819951983 6.359869885 52.820044933 6.35910946 52.820101686 6.358906215 52.820114014 6.358672174 52.820127718 6.357653893 52.820148928 6.357541055 52.82015097 6.35692356 52.820162172 6.355155103 52.820169237 6.355025847 52.820152311 6.354671763 52.81997881 6.353195638 52.819179118 6.352976004 52.819057884 6.352687161 52.818899015 6.352605263 52.818853618 6.351724891 52.818368692 6.351617181 52.818308899 6.351424881 52.818154862 6.351400358 52.818135962 6.351284818 52.818067808 6.350937851 52.817879071 6.35071669 52.817761778 6.350362027 52.817570856 6.350274094 52.817514273 6.349976834 52.817361644 6.349030758 52.816837344 6.34883237 52.816722114 6.348382428 52.816476906 6.348199334 52.81638233 6.348193624 52.816375637 6.347484967 52.815990399 6.347150435 52.81580717 6.346967463 52.815707537 6.346797562 52.815611729 6.346663186 52.815540351 6.346566876 52.815672002 6.345615164 52.816325612 6.345545527 52.816373917 6.344979697 52.816762667 6.344612652 52.817010516 6.344527306 52.817061192 6.343893809 52.817515076 6.343473932 52.817785251 6.34322911 52.817963029 6.342969029 52.818131937 6.342746391 52.818296053 6.342553351 52.818425105 6.342512516 52.818455203 6.342441006 52.81846027 6.342352854 52.818435698 6.341781394 52.818271764 6.341493057 52.818187008 6.341208768 52.818107275 6.34105914 52.818069713 6.340831416 52.81800076 6.34035663 52.817826497 6.340159309 52.817759547 6.34004567 52.817735177 6.339855674 52.817663674 6.339395861 52.817484794 6.339152624 52.817395178 6.338931867 52.817326728 6.338813776 52.817300146 6.338265358 52.815007164 6.338214969 52.814693575 6.338204929 52.814626251 6.338167812 52.814507467 6.337880856 52.813343663 6.337871012 52.813231963 6.337835132 52.813073848 6.337778909 52.812982177 6.338033114 52.812820627 6.338231226 52.812690979 6.338363805 52.812627574 6.338635096 52.812537784 6.339950585 52.812124539 6.340462077 52.81195475 6.340748344 52.811840121 6.34091317 52.811725339 6.34131611 52.81141374 6.341521291 52.811258191 6.341995965 52.810888724 6.34262854 52.810396099 6.342704836 52.810345495 6.342790852 52.810272908 6.343206021 52.809938738 6.34320603 52.809917954 6.343066719 52.809842119 6.34307761 52.809778558 6.343017497 52.80974253 6.341912258 52.809070602 6.341916714 52.80900934 6.341691151 52.80886735 6.340855191 52.808353342 6.340658854 52.808244256 6.340658328 52.808220108 6.34072188 52.808180281 6.340820931 52.808110398 6.340729866 52.807993732 6.340355103 52.807587246 6.340082333 52.807426533 6.34009678 52.807355643 6.339732867 52.807117021 6.340518785 52.806559145 6.341089503 52.806919687 6.344536044 52.809072594 6.344617723 52.809130351 6.344618079 52.809157312 6.344682709 52.809209032 6.344723109 52.809212639 6.344785183 52.80922169 6.344973638 52.809351052 6.345213718 52.809499099 6.345391207 52.809603834 6.345655682 52.809765164 6.345915537 52.809927093 6.345991661 52.809879297 6.346016737 52.809849887 6.346067428 52.809825888 6.346175378 52.809771094 6.346745293 52.809435665 6.346890839 52.809341253 6.347118776 52.809199555 6.347138235 52.809188725 6.347248369 52.809254682 6.347240717 52.809233398 6.34732211 52.809193424 6.347512528 52.809084604 6.347879805 52.808882802 6.348110311 52.808752876 6.348136416 52.808738624 6.348083554 52.808600309 6.347943306 52.808249813 6.347750676 52.807803688 6.347455779 52.807069109 6.347186212 52.806442733 6.347108732 52.806249007 6.346669345 52.805591981 6.346494535 52.80512268 6.3463611 52.804817627 6.346186468 52.804356188 6.345967641 52.803759733 6.345877844 52.803616659 6.345898421 52.80351932 6.346024911 52.803454829 6.346318561 52.803299683 6.346594288 52.803162095 6.346765966 52.803066347 6.346955758 52.802972137 6.346701001 52.802819157 6.346289262 52.802586555 6.34601687 52.802453377 6.345676098 52.802339844 6.345404792 52.802256085 6.345174385 52.802177613 6.345141986 52.802158214 6.345428992 52.801900894 6.346259342 52.801221293 6.346308638 52.801176523 6.346550027 52.801079654 6.346550172 52.801079798 6.346758233 52.801286932 6.346861847 52.801246778 6.347276231 52.801135594 6.347581064 52.801121342 6.347642017 52.801132647 6.347751035 52.801106491 6.347830962 52.801085065 6.347535642 52.800687842 6.347535398 52.800687514 6.347503163 52.80064396 6.34729259 52.800370982 6.346972213 52.799971945 6.346726017 52.799680155 6.346494495 52.799412963 6.346264241 52.799192942 6.34600423 52.798978779 6.346046329 52.798975631 6.346330669 52.79897394 6.346284432 52.798858876 6.348293373 52.795394673 6.350315206 52.7919627 6.350445568 52.791903653 6.349530695 52.791633592 6.349368572 52.791592774 6.349227463 52.791538305 6.349113798 52.791510014 6.348128699 52.791229245 6.347923339 52.791170798 6.346328632 52.790702264 6.345980077 52.790599468 6.344962511 52.790304331 6.343385522 52.789869878 6.343161499 52.789804832 6.342947727 52.789742513 6.342665656 52.789660519 6.343173335 52.789519391 6.343451677 52.789452 6.34360079 52.789385646 6.343886483 52.789177769 6.34415205 52.789023976 6.344252975 52.788968118 6.344386598 52.788924355 6.345710166 52.788470532 6.345887008 52.78843316 6.346112229 52.788404947 6.3464558 52.788376343 6.346804332 52.788330847 6.347120304 52.788279435 6.34745791 52.788221667 6.347800758 52.788159924 6.348015332 52.788132355 6.348219442 52.788123969 6.348504516 52.78813178 6.348903234 52.788167321 6.349137999 52.788204746 6.349408019 52.788254805 6.349776274 52.788369226 6.350308228 52.78859635 6.350459267 52.788618158 6.350593599 52.788606961 6.350748721 52.788551223 6.350902625 52.788376973 6.351020044 52.788460279 6.351201961 52.788611591 6.351304354 52.788717486 6.351358884 52.788774337 6.351451329 52.78890166 6.351565683 52.78907711 6.351689032 52.789103634 6.351807028 52.789202661 6.351956616 52.78931604 6.352177884 52.789455237 6.352401667 52.789571943 6.352606098 52.789661846 6.352950378 52.789791056 6.35344637 52.789951053 6.353501229 52.789907358 6.35364105 52.789798377 6.353762346 52.789700215 6.353715597 52.789660153 6.353873559 52.789533612 6.354019847 52.789518382 6.354129857 52.789433796 6.354112038 52.789403046 6.353937302 52.789294369 6.353945178 52.78926285 6.354214973 52.789082038 6.354321771 52.789009273 6.355129001 52.789155502 6.355218635 52.788935148 6.355371479 52.788713717 6.355458305 52.78872256 6.35562595 52.788458319 6.355562536 52.788439736 6.355864406 52.787835132 6.355964134 52.787715241 6.356228548 52.787449089 6.356295359 52.787453602 6.356333603 52.787392066 6.356293426 52.787387336 6.356144712 52.787355404 6.356094857 52.787342329 6.355967434 52.787309662 6.355234083 52.787119588 6.355120632 52.787090178 6.355021435 52.78707694 6.354940449 52.787059623 6.354167001 52.786888964 6.354164671 52.786888423 6.354028197 52.785501556 6.352707581 52.785178051 6.352404123 52.785091757 6.351881649 52.784904449 6.351548525 52.784775145 6.351506479 52.784748523 6.351301001 52.784620433 6.35065428 52.784259432 6.350610459 52.784236195 6.350452876 52.784126813 6.350267514 52.784007545 6.35007616 52.783857992 6.349934958 52.783734997 6.349636842 52.783522272 6.349501567 52.78341608 6.349501673 52.783415926 6.34935565 52.783323075 6.349180657 52.783170024 6.349033792 52.783036903 6.348908623 52.782883458 6.349233523 52.782374276 6.350575537 52.780680201 6.350788004 52.780424826 6.351151576 52.780632735 6.351960501 52.781121584 6.351960501 52.781122007 6.351960667 52.781121845 6.352148418 52.78123435 6.352251674 52.781295864 6.353245814 52.781890516 6.353367151 52.781963114 6.353443895 52.782009114 6.353516413 52.782052339 6.354292104 52.782517315 6.354526106 52.782657528 6.356079854 52.783586883 6.356258714 52.783694399 6.356928183 52.784097874 6.357265071 52.784302402 6.357317661 52.784334553 6.35738058 52.784372797 6.357531555 52.784465374 6.357551792 52.784396118 6.357600622 52.784227208 6.357661344 52.784072245 6.357692472 52.78399279 6.357800171 52.783804866 6.357809966 52.783713789 6.357756588 52.783562564 6.357757548 52.783480547 6.357828181 52.783281688 6.357892316 52.783113777 6.357896835 52.783056446 6.357875007 52.783001576 6.357760949 52.782902522 6.357448495 52.782671397 6.357325204 52.78255276 6.357279428 52.782472806 6.357268725 52.782386953 6.357281397 52.782300347 6.357287655 52.78225873 6.357298155 52.782188993 6.357509193 52.781564341 6.357559731 52.781451588 6.357635159 52.781406601 6.357784329 52.781366065 6.357932004 52.781268248 6.358189198 52.781378493 6.358336495 52.781441327 6.358446445 52.781490984 6.358600837 52.7815605 6.358827482 52.781692338 6.3589117 52.781782648 6.358963897 52.78188052 6.35897888 52.781960722 6.358963092 52.782178231 6.358960551 52.782460228 6.35898551 52.782583041 6.359040357 52.782675273 6.359132187 52.782763836 6.35916743 52.782786577 6.359317834 52.782884773 6.359393789 52.782915609 6.359713685 52.782991074 6.360081611 52.783070642 6.360746731 52.783214623 6.360914616 52.783244706 6.36102274 52.783264044 6.361089242 52.783275858 6.361119219 52.783269996 6.361206145 52.783252434 6.361338265 52.783226076 6.361504601 52.783165737 6.361753613 52.783053043 6.362069537 52.782887565 6.362143519 52.78285045 6.362185213 52.782829885 6.362234227 52.78280533 6.362282781 52.78278078 6.362386976 52.782706905 6.362546809 52.782552249 6.362648863 52.782444689 6.362719238 52.78237053 6.362938516 52.782171014 6.363106587 52.782064036 6.363288738 52.781986151 6.363366991 52.781964165 6.36345124 52.781941007 6.363695232 52.781873849 6.363971055 52.781821595 6.364108045 52.781795756 6.364402933 52.781757388 6.364810633 52.781709669 6.364904499 52.781692048 6.365083018 52.781659127 6.365713311 52.78149892 6.366524689 52.781275994 6.36694548 52.781151205 6.367062319 52.781156424 6.367563981 52.781302834 6.367942318 52.781402512 6.368081483 52.78142215 6.368148885 52.781381152 6.36887035 52.780939324 6.368891361 52.78092623 6.369052165 52.780960854 6.370079662 52.781225934 6.370706879 52.780837109 6.370787593 52.780790945 6.371798907 52.781407212 6.372492051 52.781839049 6.372664694 52.781946593 6.373393994 52.782400943 6.373468441 52.782357511 6.374008352 52.782052772 6.374276922 52.781901187 6.374190515 52.781840951 6.3746178 52.781588919 6.374441776 52.781431895 6.376469355 52.780241436 6.378788452 52.778884963 6.379362794 52.778547127 6.380763294 52.77772617 6.381471674 52.777987813 6.38245581 52.778351168 6.383182906 52.778619483 6.383921768 52.778893188 6.384002587 52.778923122 6.384204254 52.778993882 6.38430577 52.779031902 6.384991827 52.77928884 6.385524704 52.779484237 6.386125247 52.779704435 6.386810035 52.779955479 6.386810009 52.779892526 6.386819495 52.779831219 6.38686127 52.779743805 6.386859078 52.77964777 6.386870519 52.779580833 6.38690933 52.779526019 6.387017146 52.779430186 6.387221463 52.779270629 6.387292489 52.779176228 6.387342238 52.779062906 6.387428239 52.779076788 6.387686755 52.779221785 6.387965776 52.779372227 6.388496207 52.778991986 6.388699622 52.77907678 6.388889003 52.779125179 6.389114968 52.779163161 6.389571162 52.77915202 6.389626769 52.779122905 6.389671716 52.778891102 6.39012159 52.779059199 6.391499839 52.779568855 6.391540948 52.779553904 6.392122232 52.778999086 6.392729622 52.778412028 6.393063191 52.778103641 6.39312216 52.77802956 6.393449031 52.777812786 6.393705434 52.777623572 6.393913353 52.777521267 6.3940926 52.777451224 6.394142074 52.777477768 6.394180921 52.777495414 6.394254857 52.777528492 6.394381523 52.777467879 6.394502589 52.777445511 6.394683832 52.777432181 6.394974887 52.777420733 6.395141073 52.777417081 6.395185676 52.777493655 6.395296579 52.777623598 6.395503222 52.777757783 6.395752015 52.77787195 6.396051055 52.778005914 6.396160896 52.778059469 6.396775603 52.778425553 6.396932841 52.778515778 6.397039034 52.778581722 6.397085168 52.778634132 6.397165564 52.778816569 6.397193124 52.778866889 6.397375749 52.778913085 6.39860507 52.779628948 6.399725229 52.780279442 6.400410151 52.780684792 6.401075453 52.781132435 6.402178168 52.781976282 6.402558198 52.782255023 6.403036996 52.782598079 6.403470971 52.782905566 6.403811073 52.783139709 6.404134704 52.783352642 6.404589253 52.783657703 6.405147269 52.784019735 6.405881458 52.784507204 6.405961462 52.784561006 6.406592652 52.785001044 6.407028645 52.785273675 6.407162382 52.78535735 6.407303421 52.785426353 6.407744676 52.785546716 6.408190437 52.785671528 6.408280901 52.785697154 6.408309104 52.785704778 6.408598695 52.785787112 6.408678919 52.785810578 6.409254255 52.785979213 6.409735055 52.786126189 6.409816941 52.786151325 6.410078447 52.78623109 6.410162895 52.786256765 6.410336228 52.786309763 6.410256063 52.786616023 6.410246311 52.786704295 6.410290957 52.786969602 6.410310223 52.787030662 6.410438606 52.787132354 6.410528597 52.78718719 6.410651645 52.787249045 6.410825368 52.787328439 6.411023554 52.787394142 6.411123691 52.787426984 6.411195825 52.787451079 6.411592919 52.787513948 6.411875511 52.787563758 6.412007359 52.787625536 6.412888941 52.788248753 6.41297566 52.788282271 6.413518031 52.788079878 6.414407515 52.787745297 6.414428417 52.787737814 6.414478281 52.787710984 6.41452128 52.787687582 6.414557191 52.787668175 6.415147298 52.787210907 6.415396855 52.787017772 6.415763593 52.786744985 6.416257576 52.786377291 6.416275489 52.786321527 6.416333271 52.785311069 6.41638731 52.784456799 6.416401438 52.784397697 6.416471163 52.783294453 6.416474268 52.783239378 6.416499964 52.782795403 6.416526292 52.782339065 6.416541895 52.781987859 6.416545116 52.781868748 6.4165466 52.781813687 6.416548427 52.781743458 6.416668982 52.781739047 6.417001148 52.781771002 6.417304262 52.781768943 6.417757981 52.781759965 6.417841477 52.781755309 6.417935559 52.781728096 6.418210239 52.781718416 6.418290222 52.781712107 6.41854404 52.781691935 6.41876726 52.781660794 6.418956846 52.781597926 6.419310779 52.781472407 6.419474296 52.781443466 6.419664538 52.781398567 6.419913343 52.781313277 6.420055941 52.781281145 6.420249767 52.781270478 6.420407395 52.781247205 6.420484599 52.781221256 6.420501316 52.781173928 6.420475418 52.78097924 6.420528592 52.78093609 6.420555067 52.780899909 6.420727244 52.780933803 6.420814623 52.780946526 6.421119821 52.780993871 6.421275204 52.781012744 6.421389933 52.781026353 6.421377187 52.781084882 6.421352749 52.781109246 6.421312489 52.781150039 6.421350841 52.781195206 6.421441487 52.781277553 6.421552734 52.781369269 6.421635516 52.781461794 6.421912502 52.781912693 6.422000368 52.782043929 6.422150181 52.782238669 6.422278685 52.782384159 6.422425454 52.782528368 6.422589974 52.782669051 6.422721496 52.782765646 6.422926644 52.782910471 6.42301707 52.782983269 6.423305211 52.783131303 6.423519929 52.783229983 6.423686594 52.783275154 6.423904728 52.783332237 6.42416048 52.783373826 6.424749699 52.783442842 6.427092995 52.783838643 6.427865018 52.7839684 6.428061658 52.783988028 6.428444412 52.784042539 6.42832948 52.783923337 6.428185394 52.783785853 6.428143242 52.783717693 6.428083751 52.783621598 6.427818519 52.783103205 6.427650516 52.782806964 6.427536403 52.78260518 6.428291618 52.782525565 6.428251197 52.782432672 6.42872124 52.782389242 6.428971157 52.782380319 6.42906629 52.782387912 6.429135852 52.782420445 6.42914387 52.782436103 6.42943118 52.782986317 6.42978721 52.783698825 6.42981638 52.783834505 6.429822236 52.783954098 6.429832888 52.784168018 6.429717393 52.784229694 6.429425185 52.784447386 6.428916772 52.784884351 6.428929154 52.784966816 6.428965091 52.785075474 6.429035653 52.785247302 6.429112205 52.785369086 6.429252081 52.785524019 6.429469831 52.785749047 6.429842413 52.786144043 6.430240278 52.786550049 6.43037303 52.78669718 6.430403111 52.786754211 6.430412265 52.786817604 6.430394946 52.786858761 6.430299861 52.786931493 6.430104102 52.787046673 6.430003445 52.787109342 6.429957928 52.787152993 6.429942943 52.78721435 6.429980042 52.787293789 6.430033515 52.787409034 6.430131521 52.78754636 6.430133099 52.787612626 6.430123788 52.787941311 6.430098723 52.787978041 6.430007905 52.78802602 6.429734911 52.788146931 6.429567195 52.788233779 6.429485215 52.788292916 6.429454749 52.788336431 6.429457155 52.788437519 6.429506001 52.788562914 6.429580137 52.788651019 6.429688924 52.788754545 6.429934903 52.788948429 6.430274248 52.789191492 6.430417757 52.789303702 6.43053244 52.78941167 6.430655748 52.789521809 6.43080723 52.789599123 6.430987143 52.78967394 6.431348559 52.789880292 6.43168417 52.790092488 6.432401225 52.790505239 6.432654016 52.790614801 6.432842303 52.790681118 6.433001491 52.790721848 6.433191946 52.790752756 6.433396411 52.790768936 6.433749895 52.790768642 6.433806348 52.790969239 6.433990468 52.791083896 6.43415406 52.791153797 6.434409315 52.791249853 6.434665007 52.791315574 6.434844171 52.791348826 6.434930731 52.791364916 6.434984007 52.791374558 6.43528416 52.791420226 6.435450487 52.791468755 6.435585174 52.791492286 6.435727918 52.79150395 6.435954678 52.791512624 6.436395892 52.791499755 6.436799044 52.791483847 6.43678046 52.791587929 6.436817134 52.791678041 6.436911585 52.791781688 6.437005121 52.791847146 6.43711657 52.791915816 6.437175222 52.791956306 6.437326918 52.791867902 6.437403223 52.791823416 6.437612515 52.79169294 6.43872543 52.791001205 6.438895011 52.79089579 6.439011644 52.790823424 6.439377739 52.790596067 6.440496101 52.789911572 6.440559033 52.789870008 6.440674787 52.789799894 6.440748981 52.789860464 6.441092036 52.790139411 6.442325214 52.791126104 6.442790114 52.791500021 6.443691956 52.791117365 6.443997254 52.791366306 6.444466906 52.791754217 6.444974317 52.792170439 6.445861326 52.79289897 6.447346978 52.79203926 6.447753248 52.792362563 6.448248863 52.792013261 6.448749835 52.791713335 6.448840597 52.791654109 6.448872055 52.791636657 6.448880657 52.791648138 6.448892752 52.791652938 6.448900841 52.791652587 6.448913746 52.791648077 6.449045281 52.791569299 6.449059006 52.791563047 6.449067824 52.791561701 6.449073525 52.79156263 6.44907893 52.791567246 6.449158081 52.791697964 6.44916218 52.791698862 6.449170846 52.791697967 6.449179041 52.791699388 6.44919658 52.791727891 6.449525018 52.792260839 6.450063239 52.793086661 6.450069257 52.793139002 6.450208865 52.79333096 6.450306064 52.793467681 6.450419925 52.79362746 6.450478567 52.79370821 6.450495383 52.793731553 6.450611545 52.793897485 6.450721151 52.794053499 6.450831725 52.794213954 6.450869377 52.794269196 6.450986334 52.794420759 6.451189235 52.79468857 6.45127376 52.794803799 6.451250217 52.794810579 6.451257404 52.794818369 6.45149804 52.795142168 6.45176268 52.795495787 6.451970536 52.795783937 6.452012833 52.79585322 6.452181753 52.796085897 6.45215254 52.79615279 6.452362515 52.796370558 6.452573351 52.796649404 6.452654255 52.796697788 6.452779332 52.796868123 6.452947782 52.797106087 6.45310402 52.79733937 6.453117808 52.797367179 6.453381418 52.797714466 6.453628986 52.79807086 6.453803471 52.798316363 6.454075874 52.798683254 6.454352614 52.799059381 6.45454158 52.799330466 6.454603023 52.799375842 6.454876097 52.799755712 6.455130093 52.800087004 6.455476793 52.800586869 6.455807673 52.80109438 6.455999454 52.801425967 6.45615796 52.801700433 6.456362824 52.802044683 6.456517877 52.802322108 6.456628792 52.802540262 6.456797834 52.802872961 6.456890168 52.803059493 6.456951941 52.80319089 6.45701157 52.803329178 6.457039572 52.803365728 6.45708257 52.803461301 6.457076012 52.803487846 6.457132642 52.803615192 6.457157659 52.803633823 6.457259985 52.803866227 6.45732579 52.804016265 6.457428124 52.804258573 6.45743888 52.804321818 6.457465392 52.80438355 6.457483741 52.804404955 6.457514511 52.804479463 6.457551035 52.804601247 6.457586792 52.804693478 6.457667182 52.80493104 6.457690485 52.804959743 6.457742273 52.805103957 6.457812093 52.805324025 6.457871294 52.805504149 6.457915569 52.805640828 6.457951599 52.805759911 6.45804588 52.806052862 6.45809144 52.80620878 6.458109563 52.806239543 6.458058394 52.806273357 6.45807776 52.806305356 6.45813729 52.806550833 6.458201285 52.806806031 6.458247402 52.806999062 6.458291443 52.807189828 6.458347489 52.807413911 6.458417858 52.807708201 6.458465068 52.807901608 6.458489679 52.808002459 6.458553746 52.808276125 6.458622465 52.808564147 6.458651928 52.808708013 6.458660387 52.808741065 6.458671595 52.808758337 6.458683479 52.808843287 6.458707283 52.808974145 6.458729865 52.809103478 6.458783147 52.809329095 6.458832984 52.809539393 6.458870158 52.809709208 6.458921134 52.809938117 6.458981056 52.810187096 6.459028912 52.810400575 6.459115733 52.810742464 6.459132463 52.810750818 6.459216097 52.81105348 6.4592337 52.811108585 6.459269631 52.811182031 6.459286859 52.811230785 6.459238158 52.811222029 6.459402851 52.811784822 6.459390338 52.81185225 6.459459343 52.811963217 6.459479879 52.811996232 6.459660961 52.812386865 6.459743277 52.812614182 6.459789605 52.812734223 6.459921897 52.813024584 6.459962198 52.813125015 6.460021815 52.813270955 6.460019251 52.813286796 6.460016573 52.81332516 6.460024265 52.813392685 6.460027708 52.813467744 6.460026705 52.813542411 6.460020623 52.813603499 6.460001232 52.813675905 6.459962336 52.813718128 6.459925165 52.813803449 6.459852622 52.813938623 6.459794443 52.814038934 6.459717014 52.814163629 6.459632789 52.814294264 6.459553479 52.81440687 6.459464158 52.814530073 6.459393307 52.814621186 6.459285209 52.814785576 6.459265103 52.814821033 6.459221282 52.814925645 6.459242185 52.815013551 6.45925666 52.815097723 6.459268773 52.815154261 6.459289985 52.815211787 6.459315379 52.815297092 6.459342447 52.815374437 6.459373968 52.81544403 6.459396663 52.815485168 6.459471934 52.815561621 6.459503494 52.815600729 6.459583812 52.815667043 6.459658301 52.815728512 6.459743515 52.815788177 6.459906516 52.815869529 6.459966981 52.815898652 6.460079006 52.815971844 6.460242734 52.816080286 6.46043219 52.816160384 6.460372309 52.816218918 6.4601506 52.816476578 6.459808779 52.816924312 6.460019797 52.817007274 6.460495093 52.817123094 6.46042238 52.817184962 6.46005364 52.817498732 6.459523766 52.818299853 6.459476816 52.818381877 6.460924821 52.817937094 6.461331956 52.817832022 6.461525612 52.817793025 6.461764049 52.817770178 6.461941905 52.817783062 6.462618091 52.81789958 6.462883343 52.817945287 6.463987391 52.818128037 6.464087338 52.818144581 6.464087548 52.818144789 6.465126358 52.819185802 6.465280408 52.819219796 6.465526318 52.819472589 6.465879995 52.819846859 6.466382911 52.820378743 6.46684123 52.820840814 6.46746123 52.821504194 6.468061681 52.82215427 6.468530106 52.822667357 6.468692328 52.822852936 6.468745831 52.822926034 6.468788542 52.822984627 6.469339796 52.823705916 6.470828078 52.825680293 6.471403209 52.826436182 6.471809934 52.8269633 6.472212638 52.827496068 6.472792035 52.828263147 6.473286455 52.828912475 6.473619664 52.829362177 6.474082695 52.829969659 6.474216613 52.830143131 6.474398604 52.830375704 6.474662901 52.830701332 6.475180126 52.831333032 6.475245667 52.831413879 6.475939146 52.832232704 6.476351064 52.832712573 6.476668944 52.83308433 6.477573732 52.834108481 6.478263667 52.834865532 6.479252844 52.835960234 6.479768855 52.836566086 6.480174836 52.837055545 6.480105204 52.837075695 6.48016171 52.837148767 6.480154296 52.837150893 6.48051755 52.83761936 6.480709152 52.837860351 6.479296851 52.837952929 6.476981235 52.838115564 6.47693316 52.838116004 6.476888164 52.838101855 6.476862192 52.838089933 6.476877859 52.838085424 6.476800822 52.838020951 6.476758797 52.838030474 6.476590185 52.83806684 6.476567591 52.838072103 6.476480635 52.838090872 6.476254983 52.838136746 6.476056457 52.838163834 6.475982133 52.838168446 6.475862671 52.838176279 6.47438347 52.838272342 6.470994393 52.83850091 6.470793282 52.838517342 6.470660207 52.838528101 6.470374075 52.838548113 6.469983232 52.838572446 6.469739201 52.838560057 6.469420641 52.838525313 6.469282486 52.838499605 6.468657804 52.838370461 6.468398782 52.838314392 6.468310605 52.838302834 6.468241961 52.838293346 6.468172867 52.838284424 6.46813517 52.838279149 6.468053463 52.838275956 6.467973598 52.838272186 6.467753944 52.838270246 6.467527253 52.838274546 6.467270115 52.8382853 6.466833099 52.838317905 6.465749702 52.838413088 6.465687445 52.838418145 6.465371531 52.838443469 6.464369126 52.838531728 6.463674299 52.838595295 6.463295089 52.838630736 6.462973131 52.838665096 6.462671959 52.838705446 6.462106353 52.838818393 6.461930544 52.838854803 6.46173003 52.83889593 6.460850716 52.839077418 6.459813442 52.839286156 6.458538996 52.839545325 6.458361051 52.839580063 6.456826992 52.839901647 6.456056513 52.840068642 6.455941855 52.840093262 6.454086633 52.840464871 6.453922453 52.840493862 6.453785591 52.840511377 6.453648305 52.840521029 6.452763231 52.840487937 6.452084266 52.840461983 6.450683475 52.840402024 6.449498914 52.840345737 6.449331731 52.840337115 6.449217713 52.84033083 6.448802908 52.840314862 6.448558189 52.840302999 6.44824592 52.840288364 6.446714262 52.840225028 6.44472048 52.84013544 6.444281933 52.840115735 6.444017361 52.840107408 6.443955225 52.840107958 6.443843468 52.840108949 6.443612361 52.840113243 6.443392712 52.840121366 6.443300118 52.840128366 6.443163266 52.840146429 6.440995028 52.840525099 6.440083631 52.840679192 6.439216527 52.840833448</gml:posList>
</gml:LinearRing>
</gml:exterior>
</gml:PolygonPatch>
</gml:patches>
</gml:Surface>
</gml:surfaceMember>
</gml:MultiSurface>
  </ps:geometry>
  <ps:inspireID>
    <base:Identifier>
      <base:localId><!-- String value. --></base:localId>
      <base:namespace><!-- String value. --></base:namespace>
      <base:versionId nilReason=""><!-- String value. --></base:versionId>
    </base:Identifier>
  </ps:inspireID>
  <ps:legalFoundationDate nilReason="">2000-01-01T00:00:00</ps:legalFoundationDate>
  <!-- dit is een dummy datum. Deze moet nog worden aangepast -->
  <ps:legalFoundationDocument nilReason="" owns="false">
    <gmd:CI_Citation id="id-f6d54c36-42d5-4de4-aa2f-46fa4987640eCIC" uuid="">
      <gmd:title gco:nilReason="">
        <gco:CharacterString><!-- String value. --></gco:CharacterString>
      </gmd:title>
      <gmd:alternateTitle gco:nilReason="">
        <gco:CharacterString><!-- String value. --></gco:CharacterString>
      </gmd:alternateTitle>
      <gmd:date uuidref="" xlink:type="simple" xlink:href="" xlink:title="" xlink:show="other" xlink:actuate="other">
        <gmd:CI_Date id="id-f6d54c36-42d5-4de4-aa2f-46fa4987640eD" uuid="">
          <gmd:date gco:nilReason="">            
          </gmd:date>
          <gmd:dateType>
            <gmd:CI_DateTypeCode codeList="" codeListValue="" codeSpace=""><!-- String value. --></gmd:CI_DateTypeCode>
          </gmd:dateType>
        </gmd:CI_Date>
      </gmd:date>
      <gmd:edition gco:nilReason="">
        <gco:CharacterString><!-- String value. --></gco:CharacterString>
      </gmd:edition>
      <gmd:editionDate gco:nilReason="">
      </gmd:editionDate>
      <gmd:identifier uuidref="" xlink:type="simple" xlink:href="" xlink:title="" xlink:show="other" xlink:actuate="other">
        <gmd:MD_Identifier id="id-f6d54c36-42d5-4de4-aa2f-46fa4987640eMD3" uuid="">
          <gmd:authority uuidref="" xlink:type="simple" xlink:href="" xlink:title="" xlink:show="other" xlink:actuate="other">
          </gmd:authority>
          <gmd:code gco:nilReason="">
            <gco:CharacterString><!-- String value. --></gco:CharacterString>
          </gmd:code>
        </gmd:MD_Identifier>
      </gmd:identifier>
      <gmd:citedResponsibleParty uuidref="" xlink:type="simple" xlink:href="" xlink:title="" xlink:show="other" xlink:actuate="other">
        <gmd:CI_ResponsibleParty id="id-f6d54c36-42d5-4de4-aa2f-46fa4987640eCIR" uuid="">
          <gmd:individualName gco:nilReason="">
            <gco:CharacterString><!-- String value. --></gco:CharacterString>
          </gmd:individualName>
          <gmd:organisationName gco:nilReason="">
            <gco:CharacterString><!-- String value. --></gco:CharacterString>
          </gmd:organisationName>
          <gmd:positionName gco:nilReason="">
            <gco:CharacterString><!-- String value. --></gco:CharacterString>
          </gmd:positionName>
          <gmd:contactInfo uuidref="" xlink:type="simple" xlink:href="" xlink:title="" xlink:show="other" xlink:actuate="other">
            <gmd:CI_Contact id="id-f6d54c36-42d5-4de4-aa2f-46fa4987640eCIC2" uuid="">
              <gmd:phone uuidref="" xlink:type="simple" xlink:href="" xlink:title="" xlink:show="other" xlink:actuate="other">
                <gmd:CI_Telephone id="id-f6d54c36-42d5-4de4-aa2f-46fa4987640eCIT" uuid="">
                  <gmd:voice gco:nilReason="">
                    <gco:CharacterString><!-- String value. --></gco:CharacterString>
                  </gmd:voice>
                  <gmd:facsimile gco:nilReason="">
                    <gco:CharacterString><!-- String value. --></gco:CharacterString>
                  </gmd:facsimile>
                </gmd:CI_Telephone>
              </gmd:phone>
              <gmd:address uuidref="" xlink:type="simple" xlink:href="" xlink:title="" xlink:show="other" xlink:actuate="other">
                <gmd:CI_Address id="id-f6d54c36-42d5-4de4-aa2f-46fa4987640eCIA" uuid="">
                  <gmd:deliveryPoint gco:nilReason="">
                    <gco:CharacterString><!-- String value. --></gco:CharacterString>
                  </gmd:deliveryPoint>
                  <gmd:city gco:nilReason="">
                    <gco:CharacterString><!-- String value. --></gco:CharacterString>
                  </gmd:city>
                  <gmd:administrativeArea gco:nilReason="">
                    <gco:CharacterString><!-- String value. --></gco:CharacterString>
                  </gmd:administrativeArea>
                  <gmd:postalCode gco:nilReason="">
                    <gco:CharacterString><!-- String value. --></gco:CharacterString>
                  </gmd:postalCode>
                  <gmd:country gco:nilReason="">
                    <gco:CharacterString><!-- String value. --></gco:CharacterString>
                  </gmd:country>
                  <gmd:electronicMailAddress gco:nilReason="">
                    <gco:CharacterString><!-- String value. --></gco:CharacterString>
                  </gmd:electronicMailAddress>
                </gmd:CI_Address>
              </gmd:address>
              <gmd:onlineResource uuidref="" xlink:type="simple" xlink:href="" xlink:title="" xlink:show="other" xlink:actuate="other">
                <gmd:CI_OnlineResource id="id-f6d54c36-42d5-4de4-aa2f-46fa4987640eCIO" uuid="">
                  <gmd:linkage>
                    <gmd:URL><!-- Any URI value. --></gmd:URL>
                  </gmd:linkage>
                  <gmd:protocol gco:nilReason="">
                    <gco:CharacterString><!-- String value. --></gco:CharacterString>
                  </gmd:protocol>
                  <gmd:applicationProfile gco:nilReason="">
                    <gco:CharacterString><!-- String value. --></gco:CharacterString>
                  </gmd:applicationProfile>
                  <gmd:name gco:nilReason="">
                    <gco:CharacterString><!-- String value. --></gco:CharacterString>
                  </gmd:name>
                  <gmd:description gco:nilReason="">
                    <gco:CharacterString><!-- String value. --></gco:CharacterString>
                  </gmd:description>
                  <gmd:function>
                    <gmd:CI_OnLineFunctionCode codeList="" codeListValue="" codeSpace=""><!-- String value. --></gmd:CI_OnLineFunctionCode>
                  </gmd:function>
                </gmd:CI_OnlineResource>
              </gmd:onlineResource>
              <gmd:hoursOfService gco:nilReason="">
                <gco:CharacterString><!-- String value. --></gco:CharacterString>
              </gmd:hoursOfService>
              <gmd:contactInstructions gco:nilReason="">
                <gco:CharacterString><!-- String value. --></gco:CharacterString>
              </gmd:contactInstructions>
            </gmd:CI_Contact>
          </gmd:contactInfo>
          <gmd:role>
            <gmd:CI_RoleCode codeList="" codeListValue="" codeSpace=""><!-- String value. --></gmd:CI_RoleCode>
          </gmd:role>
        </gmd:CI_ResponsibleParty>
      </gmd:citedResponsibleParty>
      <gmd:presentationForm>
        <gmd:CI_PresentationFormCode codeList="" codeListValue="" codeSpace=""><!-- String value. --></gmd:CI_PresentationFormCode>
      </gmd:presentationForm>
      <gmd:series uuidref="" xlink:type="simple" xlink:href="" xlink:title="" xlink:show="other" xlink:actuate="other">
        <gmd:CI_Series id="id-f6d54c36-42d5-4de4-aa2f-46fa4987640eCIS" uuid="">
          <gmd:name gco:nilReason="">
            <gco:CharacterString><!-- String value. --></gco:CharacterString>
          </gmd:name>
          <gmd:issueIdentification gco:nilReason="">
            <gco:CharacterString><!-- String value. --></gco:CharacterString>
          </gmd:issueIdentification>
          <gmd:page gco:nilReason="">
            <gco:CharacterString><!-- String value. --></gco:CharacterString>
          </gmd:page>
        </gmd:CI_Series>
      </gmd:series>
      <gmd:otherCitationDetails gco:nilReason="">
        <gco:CharacterString><!-- String value. --></gco:CharacterString>
      </gmd:otherCitationDetails>
      <gmd:collectiveTitle gco:nilReason="">
        <gco:CharacterString><!-- String value. --></gco:CharacterString>
      </gmd:collectiveTitle>
      <gmd:ISBN gco:nilReason="">
        <gco:CharacterString><!-- String value. --></gco:CharacterString>
      </gmd:ISBN>
      <gmd:ISSN gco:nilReason="">
        <gco:CharacterString><!-- String value. --></gco:CharacterString>
      </gmd:ISSN>
    </gmd:CI_Citation>
  </ps:legalFoundationDocument>
  <ps:siteDesignation nilReason="">
    <ps:DesignationType>
      <ps:designationScheme codeSpace="">natura2000</ps:designationScheme>
      <ps:designation codeSpace="">proposedSiteOfCommunityImportance, proposedSpecialProtectionArea</ps:designation>
      <ps:percentageUnderDesignation>100</ps:percentageUnderDesignation>
    </ps:DesignationType>
  </ps:siteDesignation>
  <ps:siteName nilReason="">
    <gn:GeographicalName>
      <gn:language nilReason=""><!-- String value. --></gn:language>
      <gn:nativeness nilReason="" codeSpace=""><!-- String value. --></gn:nativeness>
      <gn:nameStatus nilReason="" codeSpace=""><!-- String value. --></gn:nameStatus>
      <gn:sourceOfName nilReason=""><!-- String value. --></gn:sourceOfName>
      <gn:pronunciation nilReason="">
        <gn:PronunciationOfName>
          <gn:pronunciationSoundLink nilReason=""><!-- Any URI value. --></gn:pronunciationSoundLink>
          <gn:pronunciationIPA nilReason=""><!-- String value. --></gn:pronunciationIPA>
        </gn:PronunciationOfName>
      </gn:pronunciation>
      <gn:spelling>
        <gn:SpellingOfName>
          <gn:text>Dwingelderveld</gn:text>
          <gn:script nilReason=""><!-- String value. --></gn:script>
          <gn:transliterationScheme nilReason=""><!-- String value. --></gn:transliterationScheme>
        </gn:SpellingOfName>
      </gn:spelling>
      <gn:grammaticalGender nilReason="" codeSpace=""><!-- String value. --></gn:grammaticalGender>
      <gn:grammaticalNumber nilReason="" codeSpace=""><!-- String value. --></gn:grammaticalNumber>
    </gn:GeographicalName>
  </ps:siteName>
  <ps:siteProtectionClassification nilReason="">natureConservation</ps:siteProtectionClassification>
  <!-- geen idee of "environment" de goede waarde is -->
</ps:ProtectedSite>
</base:member>
</base:SpatialDataSet>
